pyqt_messaging_GB_server_part_GB-0.0.3.data/scripts/server_run
server/__init__.py
server/add_user.py
server/config_window.py
server/core.py
server/main_window.py
server/remove_user.py
server/server_db.py
server/stat_window.py
server/common/__init__.py
server/common/decorator.py
server/common/utils.py
server/common/variables.py
server/log_project/__init__.py
server/log_project/config_client_log.py
server/log_project/config_server_log.py
server/unit_tests/__init__.py
server/unit_tests/log_decorator.py
server/unit_tests/test_client.py
server/unit_tests/test_server.py
server/unit_tests/test_utils.py
pyqt_messaging_GB_server_part_GB-0.0.3.dist-info/METADATA
pyqt_messaging_GB_server_part_GB-0.0.3.dist-info/WHEEL
pyqt_messaging_GB_server_part_GB-0.0.3.dist-info/top_level.txt
pyqt_messaging_GB_server_part_GB-0.0.3.dist-info/RECORD
